Workbook

Sheet Só preço
A1: Exemplo cálculo do jogo de empresas com a variável Preço
B2: Decisões | D2: Cálculos
A3: Empresa | B3: Preço | C3: Quant. a ser produzida | D3: Dif. Média-Preço | E3: Dif. % Preço-média | F3: Faturamento da empresa | G3: Quantidade vendida | H3: Dif. Qtde. Vend-Prev.
A4: 1 | B4: 10 | C4: 5000 | D4: =$B$9-B4 -> 0.4 | E4: =D4/$B$9 -> 0.038461538 | F4: =$B$15*(1+E4) -> 51923.077 | G4: =F4/B4 -> 5192.3077 | H4: =G4-C4 -> 192.30769
A5: 2 | B5: 7 | C5: 9000 | D5: =$B$9-B5 -> 3.4 | E5: =D5/$B$9 -> 0.32692308 | F5: =$B$15*(1+E5) -> 66346.154 | G5: =F5/B5 -> 9478.022 | H5: =G5-C5 -> 478.02198
A6: 3 | B6: 8 | C6: 7000 | D6: =$B$9-B6 -> 2.4 | E6: =D6/$B$9 -> 0.23076923 | F6: =$B$15*(1+E6) -> 61538.462 | G6: =F6/B6 -> 7692.3077 | H6: =G6-C6 -> 692.30769
A7: 4 | B7: 12 | C7: 4000 | D7: =$B$9-B7 -> -1.6 | E7: =D7/$B$9 -> -0.15384615 | F7: =$B$15*(1+E7) -> 42307.692 | G7: =F7/B7 -> 3525.641 | H7: =G7-C7 -> -474.35897
A8: 5 | B8: 15 | C8: 2000 | D8: =$B$9-B8 -> -4.6 | E8: =D8/$B$9 -> -0.44230769 | F8: =$B$15*(1+E8) -> 27884.615 | G8: =F8/B8 -> 1858.9744 | H8: =G8-C8 -> -141.02564
A9: Média/Total | B9: =AVERAGE(B4:B8) -> 10.4 | E9: =SUM(E4:E8) -> 0 | F9: =SUM(F4:F8) -> 250000
B11: Sazonalidade Total | F11: Decisões das equipes
B12: 250000
B14: Sazonalidade Média
B15: =B12/A8 -> 50000

Sheet Preço x Propaganda
A1: Exemplo cálculo do jogo de empresas com a variáveis Preço e Propaganda
B2: Decisões | E2: Cálculos
A3: Empresa | B3: Preço | C3: Quant. a ser produzida | D3: Propaganda | E3: Dif. Média-Preço | F3: Dif. % Média-Preço | G3: Dif. Propa-Média | H3: Dif. % Prop-média | I3: Faturamento da empresa | J3: Quantidade vendida | K3: Dif. Qtde. Vend-Prev.
A4: 1 | B4: 10 | C4: 5000 | D4: 9000 | E4: =$B$9-B4 -> 0.4 | F4: =E4/$B$9 -> 0.038461538 | G4: =D4-D$9 -> -3800 | H4: =G4/D$9 -> -0.296875 | I4: =B$15*(1+F4+H4) -> 37079.327 | J4: =I4/B4 -> 3707.9327 | K4: =J4-C4 -> -1292.0673
A5: 2 | B5: 7 | C5: 9000 | D5: 12000 | E5: =$B$9-B5 -> 3.4 | F5: =E5/$B$9 -> 0.32692308 | G5: =D5-D$9 -> -800 | H5: =G5/D$9 -> -0.0625 | I5: =B$15*(1+F5+H5) -> 63221.154 | J5: =I5/B5 -> 9031.5934 | K5: =J5-C5 -> 31.593407
A6: 3 | B6: 8 | C6: 7000 | D6: 15000 | E6: =$B$9-B6 -> 2.4 | F6: =E6/$B$9 -> 0.23076923 | G6: =D6-D$9 -> 2200 | H6: =G6/D$9 -> 0.171875 | I6: =B$15*(1+F6+H6) -> 70132.212 | J6: =I6/B6 -> 8766.5264 | K6: =J6-C6 -> 1766.5264
A7: 4 | B7: 12 | C7: 4000 | D7: 18000 | E7: =$B$9-B7 -> -1.6 | F7: =E7/$B$9 -> -0.15384615 | G7: =D7-D$9 -> 5200 | H7: =G7/D$9 -> 0.40625 | I7: =B$15*(1+F7+H7) -> 62620.192 | J7: =I7/B7 -> 5218.3494 | K7: =J7-C7 -> 1218.3494
A8: 5 | B8: 15 | C8: 2000 | D8: 10000 | E8: =$B$9-B8 -> -4.6 | F8: =E8/$B$9 -> -0.44230769 | G8: =D8-D$9 -> -2800 | H8: =G8/D$9 -> -0.21875 | I8: =B$15*(1+F8+H8) -> 16947.115 | J8: =I8/B8 -> 1129.8077 | K8: =J8-C8 -> -870.19231
A9: Média/Total | B9: =AVERAGE(B4:B8) -> 10.4 | D9: =AVERAGE(D4:D8) -> 12800 | F9: =SUM(F4:F8) -> 0 | H9: =SUM(H4:H8) -> 0 | I9: =SUM(I4:I8) -> 250000
B11: Sazonalidade Total | F11: Decisões das equipes
B12: 250000
B14: Sazonalidade Média
B15: =B12/A8 -> 50000

Sheet Preço x Propaganda x Vendedor
A1: Exemplo cálculo do jogo de empresas com a variáveis Preço, Propaganda e Vendedores
B2: Decisões | F2: Cálculos
A3: Empresa | B3: Preço | C3: Quant. a ser produzida | D3: Propaganda | E3: Vendedores | F3: Dif. Média-Preço | G3: Dif. % Média-Preço | H3: Dif. Propa-Média | I3: Dif. % Prop-média | J3: Dif. Vend-media | K3: Dif. % Vend-média | L3: Faturamento da empresa | M3: Quant. vendida | N3: Dif. Qtde. Prev-Vend.
A4: 1 | B4: 10 | C4: 5000 | D4: 9000 | E4: 8 | F4: =$B$9-B4 -> 0.4 | G4: =F4/$B$9 -> 0.038461538 | H4: =D4-D$9 -> -3800 | I4: =H4/D$9 -> -0.296875 | J4: =E4-E$9 -> -1.4 | K4: =J4/E$9 -> -0.14893617 | L4: =B$15*(1+G4+I4+K4) -> 29632.518 | M4: =L4/B4 -> 2963.2518 | N4: =C4-M4 -> 2036.7482
A5: 2 | B5: 7 | C5: 9000 | D5: 12000 | E5: 10 | F5: =$B$9-B5 -> 3.4 | G5: =F5/$B$9 -> 0.32692308 | H5: =D5-D$9 -> -800 | I5: =H5/D$9 -> -0.0625 | J5: =E5-E$9 -> 0.6 | K5: =J5/E$9 -> 0.063829787 | L5: =B$15*(1+G5+I5+K5) -> 66412.643 | M5: =L5/B5 -> 9487.5205 | N5: =C5-M5 -> -487.52046
A6: 3 | B6: 8 | C6: 7000 | D6: 15000 | E6: 12 | F6: =$B$9-B6 -> 2.4 | G6: =F6/$B$9 -> 0.23076923 | H6: =D6-D$9 -> 2200 | I6: =H6/D$9 -> 0.171875 | J6: =E6-E$9 -> 2.6 | K6: =J6/E$9 -> 0.27659574 | L6: =B$15*(1+G6+I6+K6) -> 83961.999 | M6: =L6/B6 -> 10495.25 | N6: =C6-M6 -> -3495.2498
A7: 4 | B7: 12 | C7: 4000 | D7: 18000 | E7: 7 | F7: =$B$9-B7 -> -1.6 | G7: =F7/$B$9 -> -0.15384615 | H7: =D7-D$9 -> 5200 | I7: =H7/D$9 -> 0.40625 | J7: =E7-E$9 -> -2.4 | K7: =J7/E$9 -> -0.25531915 | L7: =B$15*(1+G7+I7+K7) -> 49854.235 | M7: =L7/B7 -> 4154.5196 | N7: =C7-M7 -> -154.51957
A8: 5 | B8: 15 | C8: 2000 | D8: 10000 | E8: 10 | F8: =$B$9-B8 -> -4.6 | G8: =F8/$B$9 -> -0.44230769 | H8: =D8-D$9 -> -2800 | I8: =H8/D$9 -> -0.21875 | J8: =E8-E$9 -> 0.6 | K8: =J8/E$9 -> 0.063829787 | L8: =B$15*(1+G8+I8+K8) -> 20138.605 | M8: =L8/B8 -> 1342.5736 | N8: =C8-M8 -> 657.42635
A9: Média/Total | B9: =AVERAGE(B4:B8) -> 10.4 | D9: =AVERAGE(D4:D8) -> 12800 | E9: =AVERAGE(E4:E8) -> 9.4 | G9: =SUM(G4:G8) -> 0 | I9: =SUM(I4:I8) -> 0 | K9: =SUM(K4:K8) -> -1.9428903e-16 | L9: =SUM(L4:L8) -> 250000
B11: Sazonalidade Total | F11: Decisões das equipes
B12: 250000
B14: Sazonalidade Média
B15: =B12/A8 -> 50000

Sheet Dem Resultados
A1: Demonstrativo de Resultados
A2: Empresa | B2: Taxa/regras | C2: Empresa 1 | D2: Empresa 2 | E2: Empresa 3 | F2: Empresa 4 | G2: Empresa 5
A3: Receita de vendas (faturamento) | C3: ='Preço x Propaganda x Vendedor'!L4 -> 29632.518 | D3: ='Preço x Propaganda x Vendedor'!L5 -> 66412.643 | E3: ='Preço x Propaganda x Vendedor'!L6 -> 83961.999 | F3: ='Preço x Propaganda x Vendedor'!L7 -> 49854.235 | G3: ='Preço x Propaganda x Vendedor'!L8 -> 20138.605 | I3: Decisões
I4: das equipes
A5: Despesas
A6: Propaganda | C6: ='Preço x Propaganda x Vendedor'!D4 -> 9000 | D6: ='Preço x Propaganda x Vendedor'!D5 -> 12000 | E6: ='Preço x Propaganda x Vendedor'!D6 -> 15000 | F6: ='Preço x Propaganda x Vendedor'!D7 -> 18000 | G6: ='Preço x Propaganda x Vendedor'!D8 -> 10000
A7: Vendedores | C7: ='Preço x Propaganda x Vendedor'!E4 -> 8 | D7: ='Preço x Propaganda x Vendedor'!E5 -> 10 | E7: ='Preço x Propaganda x Vendedor'!E6 -> 12 | F7: ='Preço x Propaganda x Vendedor'!E7 -> 7 | G7: ='Preço x Propaganda x Vendedor'!E8 -> 10 | I7: Regras
A8: Salário Vendedores | B8: 1500 | C8: =$B8*C7 -> 12000 | D8: =$B8*D7 -> 15000 | E8: =$B8*E7 -> 18000 | F8: =$B8*F7 -> 10500 | G8: =$B8*G7 -> 15000 | I8: estipuladas
A9: Hora Extra | B9: 10 | C9: =IF('Preço x Propaganda x Vendedor'!$N4<0,-'Preço x Propaganda x Vendedor'!$N4*'Dem Resultados'!$B9,0) -> 0 | D9: =IF('Preço x Propaganda x Vendedor'!$N5<0,-'Preço x Propaganda x Vendedor'!$N5*'Dem Resultados'!$B9,0) -> 4875.2046 | E9: =IF('Preço x Propaganda x Vendedor'!$N6<0,-'Preço x Propaganda x Vendedor'!$N6*'Dem Resultados'!$B9,0) -> 34952.498 | F9: =IF('Preço x Propaganda x Vendedor'!$N7<0,-'Preço x Propaganda x Vendedor'!$N7*'Dem Resultados'!$B9,0) -> 1545.1957 | G9: =IF('Preço x Propaganda x Vendedor'!$N8<0,-'Preço x Propaganda x Vendedor'!$N8*'Dem Resultados'!$B9,0) -> 0 | I9: Pelos
A10: Estocagem | B10: 4 | C10: =IF('Preço x Propaganda x Vendedor'!$N4>0,'Preço x Propaganda x Vendedor'!$N4*'Dem Resultados'!$B10,0) -> 8146.9926 | D10: =IF('Preço x Propaganda x Vendedor'!$N5>0,'Preço x Propaganda x Vendedor'!$N5*'Dem Resultados'!$B10,0) -> 0 | E10: =IF('Preço x Propaganda x Vendedor'!$N6>0,'Preço x Propaganda x Vendedor'!$N6*'Dem Resultados'!$B10,0) -> 0 | F10: =IF('Preço x Propaganda x Vendedor'!$N7>0,'Preço x Propaganda x Vendedor'!$N7*'Dem Resultados'!$B10,0) -> 0 | G10: =IF('Preço x Propaganda x Vendedor'!$N8>0,'Preço x Propaganda x Vendedor'!$N8*'Dem Resultados'!$B10,0) -> 2629.7054 | I10: organizadores
A12: CMV (custo da merc. Vendida) | B12: 0.2 | C12: =C3*$B12 -> 5926.5037 | D12: =D3*$B12 -> 13282.529 | E12: =E3*$B12 -> 16792.4 | F12: =F3*$B12 -> 9970.847 | G12: =G3*$B12 -> 4027.7209
A13: Salários | B13: 0.08 | C13: =C3*$B13 -> 2370.6015 | D13: =D3*$B13 -> 5313.0115 | E13: =E3*$B13 -> 6716.9599 | F13: =F3*$B13 -> 3988.3388 | G13: =G3*$B13 -> 1611.0884
A14: Aluguel | B14: 2000 | C14: =B14 -> 2000 | D14: =C14 -> 2000 | E14: =D14 -> 2000 | F14: =E14 -> 2000 | G14: =F14 -> 2000
A16: Total despesas | C16: =SUM(C6,C8:C14) -> 39444.098 | D16: =SUM(D6,D8:D14) -> 52470.745 | E16: =SUM(E6,E8:E14) -> 93461.858 | F16: =SUM(F6,F8:F14) -> 46004.381 | G16: =SUM(G6,G8:G14) -> 35268.515
A18: Resultado | C18: =C3-C16 -> -9811.5794 | D18: =D3-D16 -> 13941.899 | E18: =E3-E16 -> -9499.8593 | F18: =F3-F16 -> 3849.8534 | G18: =G3-G16 -> -15129.91
A19: Classificação | C19: =_xlfn.RANK.AVG($C18:$G18,$C18:$G18) -> 4 | D19: =_xlfn.RANK.AVG($C18:$G18,$C18:$G18) -> 1 | E19: =_xlfn.RANK.AVG($C18:$G18,$C18:$G18) -> 3 | F19: =_xlfn.RANK.AVG($C18:$G18,$C18:$G18) -> 2 | G19: =_xlfn.RANK.AVG($C18:$G18,$C18:$G18) -> 5
